mycoinlib/__init__.py
mycoinlib/btc.py
mycoinlib/eth.py
mycoinlib/ltc.py
mycoinlib/mycoin.py
mycoinlib-1.5.dist-info/METADATA
mycoinlib-1.5.dist-info/WHEEL
mycoinlib-1.5.dist-info/top_level.txt
mycoinlib-1.5.dist-info/RECORD
