Metadata-Version: 2.1
Name: mycoinlib
Version: 1.5
Requires-Dist: bitcoinlib
Requires-Dist: blockcypher
Requires-Dist: requests
Requires-Dist: eth-account
Requires-Dist: eth-keys
